sultan/__init__.py
sultan/api.py
sultan/config.py
sultan/core.py
sultan/exceptions.py
sultan/result.py
sultan/echo/__init__.py
sultan/echo/colorlog/__init__.py
sultan/echo/colorlog/colorlog.py
sultan/echo/colorlog/escape_codes.py
sultan/echo/colorlog/logging.py
sultan-0.9.1.dist-info/LICENSE
sultan-0.9.1.dist-info/METADATA
sultan-0.9.1.dist-info/WHEEL
sultan-0.9.1.dist-info/top_level.txt
sultan-0.9.1.dist-info/RECORD
